pineflow/embeddings/huggingface/__init__.py
pineflow/embeddings/huggingface/base.py
pineflow_embeddings_huggingface-0.7.1.dist-info/METADATA
pineflow_embeddings_huggingface-0.7.1.dist-info/WHEEL
pineflow_embeddings_huggingface-0.7.1.dist-info/RECORD
